majortom_scripting/__init__.py
majortom_scripting/exceptions.py
majortom_scripting/modeling_api.py
majortom_scripting/mutations.py
majortom_scripting/scripting_api.py
majortom_scripting/models/Pass.py
majortom_scripting/models/__init__.py
majortom_scripting/models/command.py
majortom_scripting/models/command_definition.py
majortom_scripting/models/groundstation.py
majortom_scripting/models/mission.py
majortom_scripting/models/satellite.py
majortom_scripting/models/system.py
majortom_scripting-1.0.1.dist-info/LICENSE
majortom_scripting-1.0.1.dist-info/METADATA
majortom_scripting-1.0.1.dist-info/WHEEL
majortom_scripting-1.0.1.dist-info/top_level.txt
majortom_scripting-1.0.1.dist-info/RECORD
