Metadata-Version: 2.1
Name: majortom-scripting
Version: 1.0.1
Summary: A package for interacting with Major Tom's Scripting API.
Home-page: https://github.com/kubos/majortom_scripting_package
Author: Kubos
Author-email: open-source@kubos.com
License: UNKNOWN
Keywords: majortom major_tom script kubos major tom satellite
Platform: UNKNOWN
Classifier: Programming Language :: Python :: 3
Classifier: License :: OSI Approved :: Apache Software License
Classifier: Operating System :: OS Independent
Requires-Python: >=3.7
